crosstray/__init__.py
crosstray/__main__.py
crosstray/cli.py
crosstray/crosstray.py
crosstray/main.py
crosstray/tray.py
crosstray/utils.py
crosstray-0.1.1.dist-info/licenses/LICENSE
crosstray-0.1.1.dist-info/METADATA
crosstray-0.1.1.dist-info/WHEEL
crosstray-0.1.1.dist-info/entry_points.txt
crosstray-0.1.1.dist-info/top_level.txt
crosstray-0.1.1.dist-info/RECORD
