Metadata-Version: 2.4
Name: crosstray
Version: 0.1.1
Summary: A lightweight Python library for creating system tray icons on Windows. (Future versions will add macOS and Linux support.) No heavy GUI dependencies—just simple status indicators, notifications, and menus.
Home-page: https://github.com/umansheikh/crosstray
Author: Uman Sheikh
Author-email: Uman Sheikh <muman014@gmail.com>
Maintainer-email: Uman Sheikh <muman014@gmail.com>
License: MIT
Project-URL: bugs, https://github.com/UmanSheikh/crosstray/issues
Project-URL: changelog, https://github.com/UmanSheikh/crosstray/blob/master/changelog.md
Project-URL: homepage, https://github.com/UmanSheikh/crosstray
Requires-Python: >=3.8
License-File: LICENSE
Requires-Dist: typer
Requires-Dist: pywin32; platform_system == "Windows"
Provides-Extra: test
Requires-Dist: coverage; extra == "test"
Requires-Dist: pytest; extra == "test"
Requires-Dist: ruff; extra == "test"
Requires-Dist: ty; extra == "test"
Requires-Dist: ipdb; extra == "test"
Provides-Extra: dev
Requires-Dist: pytest; extra == "dev"
Requires-Dist: pytest-cov; extra == "dev"
Dynamic: author
Dynamic: home-page
Dynamic: license-file
Dynamic: requires-python
